dyno_viewer/__main__.py
dyno_viewer/app.py
dyno_viewer/aws/ddb.py
dyno_viewer/aws/session.py
dyno_viewer/components/query/filter_query.py
dyno_viewer/components/query/key_filter.py
dyno_viewer/components/screens/__init__.py
dyno_viewer/components/screens/app_options.py
dyno_viewer/components/screens/confirm_dialogue.py
dyno_viewer/components/screens/create_rename_session.py
dyno_viewer/components/screens/create_saved_query.py
dyno_viewer/components/screens/error.py
dyno_viewer/components/screens/file_chooser.py
dyno_viewer/components/screens/help.py
dyno_viewer/components/screens/profile_select.py
dyno_viewer/components/screens/query_history_browser.py
dyno_viewer/components/screens/region_select.py
dyno_viewer/components/screens/saved_querys_browser.py
dyno_viewer/components/screens/table_query.py
dyno_viewer/components/screens/table_select.py
dyno_viewer/components/screens/table_session_browser.py
dyno_viewer/components/screens/table_view.py
dyno_viewer/components/screens/view_row_item.py
dyno_viewer/components/table.py
dyno_viewer/constants.py
dyno_viewer/db/__init__.py
dyno_viewer/db/manager.py
dyno_viewer/db/models.py
dyno_viewer/db/utils.py
dyno_viewer/messages.py
dyno_viewer/models.py
dyno_viewer/util/__init__.py
dyno_viewer/util/csv.py
dyno_viewer/util/json.py
dyno_viewer/util/path.py
dyno_viewer/util/util.py
dyno_viewer-0.34.0.dist-info/METADATA
dyno_viewer-0.34.0.dist-info/WHEEL
dyno_viewer-0.34.0.dist-info/entry_points.txt
dyno_viewer-0.34.0.dist-info/licenses/LICENSE
dyno_viewer-0.34.0.dist-info/RECORD
