Metadata-Version: 2.4
Name: dyno-viewer
Version: 0.34.0
Summary: 
License-File: LICENSE
Author: Rowan Self
Author-email: piesrule123@gmail.com
Requires-Python: >=3.9,<4.0
Classifier: Programming Language :: Python :: 3
Classifier: Programming Language :: Python :: 3.9
Classifier: Programming Language :: Python :: 3.10
Classifier: Programming Language :: Python :: 3.11
Classifier: Programming Language :: Python :: 3.12
Classifier: Programming Language :: Python :: 3.13
Classifier: Programming Language :: Python :: 3.14
Requires-Dist: aiosqlite (>=0.22.1,<0.23.0)
Requires-Dist: boto3 (>=1.42.34,<2.0.0)
Requires-Dist: dynamodb-json (>=1.3,<2.0)
Requires-Dist: pyclip (>=0.7.0,<0.8.0)
Requires-Dist: pyyaml (>=6.0.3,<7.0.0)
Requires-Dist: simplejson (>=3.20.2,<4.0.0)
Requires-Dist: textual (>=0.24.1,<7.4.0)
